pyspiel.so
open_spiel/__init__.py
open_spiel/python/rl_agent_policy.py
open_spiel/python/observation.py
open_spiel/python/test_utils.py
open_spiel/python/rl_tools.py
open_spiel/python/simple_nets.py
open_spiel/python/vector_env.py
open_spiel/python/policy.py
open_spiel/python/__init__.py
open_spiel/python/rl_agent.py
open_spiel/python/rl_environment.py
open_spiel/python/egt/dynamics_test.py
open_spiel/python/egt/utils_test.py
open_spiel/python/egt/alpharank.py
open_spiel/python/egt/alpharank_visualizer.py
open_spiel/python/egt/heuristic_payoff_table.py
open_spiel/python/egt/alpharank_visualizer_test.py
open_spiel/python/egt/__init__.py
open_spiel/python/egt/heuristic_payoff_table_test.py
open_spiel/python/egt/visualization.py
open_spiel/python/egt/alpharank_test.py
open_spiel/python/egt/utils.py
open_spiel/python/egt/visualization_test.py
open_spiel/python/egt/dynamics.py
open_spiel/python/egt/examples/__init__.py
open_spiel/python/egt/examples/alpharank_example.py
open_spiel/python/bots/scenarios.py
open_spiel/python/bots/bluechip_bridge_uncontested_bidding_test.py
open_spiel/python/bots/policy.py
open_spiel/python/bots/__init__.py
open_spiel/python/bots/human.py
open_spiel/python/bots/bluechip_bridge_uncontested_bidding.py
open_spiel/python/bots/bluechip_bridge.py
open_spiel/python/bots/uniform_random_test.py
open_spiel/python/bots/uniform_random.py
open_spiel/python/bots/gtp.py
open_spiel/python/bots/is_mcts_test.py
open_spiel/python/bots/bluechip_bridge_test.py
open_spiel/python/environments/iterated_matrix_game.py
open_spiel/python/environments/catch_test.py
open_spiel/python/environments/__init__.py
open_spiel/python/environments/cliff_walking_test.py
open_spiel/python/environments/cliff_walking.py
open_spiel/python/environments/catch.py
open_spiel/python/voting/base_test.py
open_spiel/python/voting/elo.py
open_spiel/python/voting/soft_condorcet_optimization.py
open_spiel/python/voting/maximal_lotteries_test.py
open_spiel-1.6.7.dist-info/RECORD
open_spiel-1.6.7.dist-info/WHEEL
open_spiel-1.6.7.dist-info/top_level.txt
open_spiel-1.6.7.dist-info/METADATA
open_spiel-1.6.7.dist-info/licenses/LICENSE
