Metadata-Version: 2.4
Name: open_spiel
Version: 1.6.7
Summary: A Framework for Reinforcement Learning in Games
Home-page: https://github.com/deepmind/open_spiel
Author: The OpenSpiel authors
Author-email: open_spiel@google.com
License: Apache 2.0
Requires-Python: >=3.10
License-File: LICENSE
Requires-Dist: pip>=20.0.2
Requires-Dist: attrs>=19.3.0
Requires-Dist: absl-py>=0.10.0
Requires-Dist: numpy>=1.21.5
Requires-Dist: scipy>=1.10.1
Requires-Dist: ml-collections>=0.1.1
Dynamic: author
Dynamic: author-email
Dynamic: description
Dynamic: description-content-type
Dynamic: home-page
Dynamic: license
Dynamic: license-file
Dynamic: requires-dist
Dynamic: requires-python
Dynamic: summary
